ansiio.py
AnsiIO-0.2.0.dist-info/LICENSE
AnsiIO-0.2.0.dist-info/METADATA
AnsiIO-0.2.0.dist-info/WHEEL
AnsiIO-0.2.0.dist-info/top_level.txt
AnsiIO-0.2.0.dist-info/RECORD
