Metadata-Version: 2.1
Name: AnsiIO
Version: 0.2.0
Summary: Library for doing stuff with ansi escapes
Home-page: https://github.com/gaming32/AnsiIO
Author: Gaming32
Author-email: gaming32i64@gmail.com
License: License :: OSI Approved :: MIT License
Platform: UNKNOWN
